Metadata-Version: 2.1
Name: python-matter-server-priyankub
Version: 1.0.16
Summary: Python Matter WebSocket Server Fixes
Author-email: Just another pretend developer <priyanku.mgr@gmail.com>
License: Apache-2.0
Platform: any
Classifier: Development Status :: 3 - Alpha
Classifier: Intended Audience :: Developers
Classifier: Environment :: Console
Classifier: Programming Language :: Python :: 3.10
Classifier: Programming Language :: Python :: 3.11
Classifier: Topic :: Home Automation
Requires-Python: >=3.10
License-File: LICENSE
Requires-Dist: aiohttp
Requires-Dist: aiorun
Requires-Dist: async-timeout
Requires-Dist: coloredlogs
Requires-Dist: dacite
Requires-Dist: orjson
Requires-Dist: home-assistant-chip-clusters ==2024.1.0
Provides-Extra: server
Requires-Dist: home-assistant-chip-core ==2024.1.0 ; extra == 'server'
Requires-Dist: cryptography ==42.0.2 ; extra == 'server'
Requires-Dist: zeroconf ==0.131.0 ; extra == 'server'
Provides-Extra: test
Requires-Dist: black ==23.12.1 ; extra == 'test'
Requires-Dist: flake8 ==7.0.0 ; extra == 'test'
Requires-Dist: flake8-docstrings ==1.7.0 ; extra == 'test'
Requires-Dist: isort ==5.13.2 ; extra == 'test'
Requires-Dist: mypy ==1.8.0 ; extra == 'test'
Requires-Dist: pylint ==3.0.3 ; extra == 'test'
Requires-Dist: pytest ==7.4.4 ; extra == 'test'
Requires-Dist: pytest-aiohttp ==1.0.5 ; extra == 'test'
Requires-Dist: pytest-cov ==4.1.0 ; extra == 'test'
